pyqttotp/__init__.py
pyqttotp/pyqttotp.py
pyqttotp-0.9.4.dist-info/LICENSE
pyqttotp-0.9.4.dist-info/METADATA
pyqttotp-0.9.4.dist-info/WHEEL
pyqttotp-0.9.4.dist-info/entry_points.txt
pyqttotp-0.9.4.dist-info/top_level.txt
pyqttotp-0.9.4.dist-info/RECORD
